{
    "info": {
        "name": "Chat App API",
        "_postman_id": "chat-app-collection-001",
        "description": "All endpoints for Chat App backend",
        "schema": "https://schema.getpostman.com/json/collection/v2.1.0/collection.json"
    },
    "item": [
        {
            "name": "Register User",
            "request": {
                "method": "POST",
                "header": [
                    {
                        "key": "Content-Type",
                        "value": "application/json"
                    }
                ],
                "body": {
                    "mode": "raw",
                    "raw": "{\n  \"username\": \"testuser\",\n  \"password\": \"testpass\"\n}"
                },
                "url": {
                    "raw": "http://localhost:8080/api/auth/register",
                    "protocol": "http",
                    "host": [
                        "localhost"
                    ],
                    "port": "8080",
                    "path": [
                        "api",
                        "auth",
                        "register"
                    ]
                }
            }
        },
        {
            "name": "Login",
            "request": {
                "method": "POST",
                "header": [
                    {
                        "key": "Content-Type",
                        "value": "application/json"
                    }
                ],
                "body": {
                    "mode": "raw",
                    "raw": "{\n  \"username\": \"testuser\",\n  \"password\": \"testpass\"\n}"
                },
                "url": {
                    "raw": "http://localhost:8080/api/auth/login",
                    "protocol": "http",
                    "host": [
                        "localhost"
                    ],
                    "port": "8080",
                    "path": [
                        "api",
                        "auth",
                        "login"
                    ]
                }
            }
        },
        {
            "name": "Get All Users",
            "request": {
                "method": "GET",
                "header": [],
                "url": {
                    "raw": "http://localhost:8080/api/auth/users",
                    "protocol": "http",
                    "host": [
                        "localhost"
                    ],
                    "port": "8080",
                    "path": [
                        "api",
                        "auth",
                        "users"
                    ]
                }
            }
        },
        {
            "name": "Send Message",
            "request": {
                "method": "POST",
                "header": [
                    {
                        "key": "Content-Type",
                        "value": "application/json"
                    }
                ],
                "body": {
                    "mode": "raw",
                    "raw": "{\n  \"senderId\": \"user1\",\n  \"receiverId\": \"user2\",\n  \"content\": \"Hello!\"\n}"
                },
                "url": {
                    "raw": "http://localhost:8080/api/messages/send",
                    "protocol": "http",
                    "host": [
                        "localhost"
                    ],
                    "port": "8080",
                    "path": [
                        "api",
                        "messages",
                        "send"
                    ]
                }
            }
        },
        {
            "name": "Get Conversation Between Two Users",
            "request": {
                "method": "GET",
                "header": [],
                "url": {
                    "raw": "http://localhost:8080/api/messages/conversation/{{user1Id}}/{{user2Id}}?page=0&size=20",
                    "protocol": "http",
                    "host": [
                        "localhost"
                    ],
                    "port": "8080",
                    "path": [
                        "api",
                        "messages",
                        "conversation",
                        "{{user1Id}}",
                        "{{user2Id}}"
                    ],
                    "query": [
                        {
                            "key": "page",
                            "value": "0"
                        },
                        {
                            "key": "size",
                            "value": "20"
                        }
                    ]
                }
            }
        },
        {
            "name": "Get Chat Room Messages",
            "request": {
                "method": "GET",
                "header": [],
                "url": {
                    "raw": "http://localhost:8080/api/messages/chatroom/{{chatRoomId}}?page=0&size=20",
                    "protocol": "http",
                    "host": [
                        "localhost"
                    ],
                    "port": "8080",
                    "path": [
                        "api",
                        "messages",
                        "chatroom",
                        "{{chatRoomId}}"
                    ],
                    "query": [
                        {
                            "key": "page",
                            "value": "0"
                        },
                        {
                            "key": "size",
                            "value": "20"
                        }
                    ]
                }
            }
        },
        {
            "name": "Mark Message as Read",
            "request": {
                "method": "PUT",
                "header": [],
                "url": {
                    "raw": "http://localhost:8080/api/messages/{{messageId}}/read",
                    "protocol": "http",
                    "host": [
                        "localhost"
                    ],
                    "port": "8080",
                    "path": [
                        "api",
                        "messages",
                        "{{messageId}}",
                        "read"
                    ]
                }
            }
        },
        {
            "name": "Get Unread Messages for User",
            "request": {
                "method": "GET",
                "header": [],
                "url": {
                    "raw": "http://localhost:8080/api/messages/unread/{{receiverId}}",
                    "protocol": "http",
                    "host": [
                        "localhost"
                    ],
                    "port": "8080",
                    "path": [
                        "api",
                        "messages",
                        "unread",
                        "{{receiverId}}"
                    ]
                }
            }
        },
        {
            "name": "Get Unread Message Count for User",
            "request": {
                "method": "GET",
                "header": [],
                "url": {
                    "raw": "http://localhost:8080/api/messages/unread-count/{{receiverId}}",
                    "protocol": "http",
                    "host": [
                        "localhost"
                    ],
                    "port": "8080",
                    "path": [
                        "api",
                        "messages",
                        "unread-count",
                        "{{receiverId}}"
                    ]
                }
            }
        }
    ]
}